acschedule.py
atcoder_schedule-0.2.4.dist-info/METADATA
atcoder_schedule-0.2.4.dist-info/WHEEL
atcoder_schedule-0.2.4.dist-info/entry_points.txt
atcoder_schedule-0.2.4.dist-info/top_level.txt
atcoder_schedule-0.2.4.dist-info/RECORD
