Metadata-Version: 2.4
Name: atcoder-schedule
Version: 0.2.4
Summary: CLI tool to get the schedule of AtCoder contests.
Project-URL: Homepage, https://github.com/kairi003/atcoder-schedule
Project-URL: Repository, https://github.com/kairi003/atcoder-schedule.git
Requires-Python: >=3.9
Requires-Dist: beautifulsoup4[lxml]>=4.13.4
Requires-Dist: requests>=2.32.3
Requires-Dist: tzdata>=2025.2
